{
  "uri" : "local://j5LgXUoTDnAEGaISplL3u9/",
  "name" : "Morocco",
  "category" : "country",
  "parent" : "local://mm81nqJ9ApBu7qJNqC6UHB/",
  "pname" : "Country Profiles (Folder)",
  "flags" : "U",
  "lvars" : [ ],
  "vars" : [ {
    "name" : "_country_identifier",
    "expr" : {
      "str" : "mo",
      "strEditMode" : ""
    }
  }, {
    "name" : "_country_name",
    "expr" : {
      "str" : "Morocco",
      "strEditMode" : ""
    }
  }, {
    "name" : "_country_longName",
    "expr" : {
      "str" : "Kingdom of Morocco",
      "strEditMode" : ""
    }
  }, {
    "name" : "_country_wpPageName",
    "expr" : {
      "str" : "Morocco",
      "strEditMode" : ""
    }
  }, {
    "name" : "_country_population",
    "expr" : {
      "num" : 32649130
    }
  }, {
    "name" : "_country_gdpExchangeRate",
    "expr" : {
      "num" : 97530000000
    }
  }, {
    "name" : "_country_gdpPerCapitaPpp",
    "expr" : {
      "num" : 5400
    }
  }, {
    "name" : "_country_googlePlaceName",
    "expr" : {
      "str" : "",
      "strEditMode" : ""
    }
  }, {
    "name" : "_country_area",
    "expr" : {
      "num" : 446550
    }
  }, {
    "name" : "_country_boundaries",
    "expr" : {
      "num" : 2018
    }
  }, {
    "name" : "_country_coastline",
    "expr" : {
      "num" : 1835
    }
  }, {
    "name" : "_country_wikiDataQid",
    "expr" : {
      "str" : "Q1028",
      "strEditMode" : ""
    }
  }, {
    "name" : "_country_locationDesc",
    "expr" : {
      "str" : "Northern Africa, bordering the North Atlantic Ocean and the Mediterranean Sea, between Algeria and Western Sahara",
      "strEditMode" : ""
    }
  }, {
    "name" : "_country_terrainDesc",
    "expr" : {
      "str" : "northern coast and interior are mountainous with large areas of bordering plateaus, intermontane valleys, and rich coastal plains",
      "strEditMode" : ""
    }
  }, {
    "name" : "_country_climateDesc",
    "expr" : {
      "str" : "Mediterranean, becoming more extreme in the interior",
      "strEditMode" : ""
    }
  }, {
    "name" : "_country_natResourcesDesc",
    "expr" : {
      "str" : "phosphates, iron ore, manganese, lead, zinc, fish, salt",
      "strEditMode" : ""
    }
  }, {
    "name" : "_country_elevationMinPlace",
    "expr" : {
      "str" : "Sebkha Tah",
      "strEditMode" : ""
    }
  }, {
    "name" : "_country_elevationMin",
    "expr" : {
      "num" : -55
    }
  }, {
    "name" : "_country_elevationMaxPlace",
    "expr" : {
      "str" : "Jebel Toubkal",
      "strEditMode" : ""
    }
  }, {
    "name" : "_country_elevationMax",
    "expr" : {
      "num" : 4165
    }
  }, {
    "name" : "_country_birthRate",
    "expr" : {
      "num" : 19
    }
  }, {
    "name" : "_country_deathRate",
    "expr" : {
      "num" : 5
    }
  }, {
    "name" : "_country_migrationRate",
    "expr" : {
      "num" : -4
    }
  }, {
    "name" : "_country_povertyRate",
    "expr" : {
      "num" : 15
    }
  }, {
    "name" : "_country_unemploymentRate",
    "expr" : {
      "num" : 9
    }
  }, {
    "name" : "_country_ageStructure",
    "expr" : {
      "json" : {
        "0-14" : 27.1,
        "15-24" : 18,
        "25-54" : 41.7,
        "55-64" : 7,
        "65-max" : 6.3
      }
    }
  }, {
    "name" : "_country_gdpByServices",
    "expr" : {
      "num" : 53.2
    }
  }, {
    "name" : "_country_gdpByIndustry",
    "expr" : {
      "num" : 31.7
    }
  }, {
    "name" : "_country_gdpByAgriculture",
    "expr" : {
      "num" : 15.1
    }
  }, {
    "name" : "country",
    "expr" : {
      "concept" : "local://RVV5lASBN39K6qUF_c6G2D/",
      "conceptName" : "Country",
      "bindings" : {
        "identifier" : "_country_identifier",
        "name" : "_country_name",
        "longName" : "_country_longName",
        "wpPageName" : "_country_wpPageName",
        "population" : "_country_population",
        "gdpExchangeRate" : "_country_gdpExchangeRate",
        "gdpPerCapitaPpp" : "_country_gdpPerCapitaPpp",
        "googlePlaceName" : "_country_googlePlaceName",
        "area" : "_country_area",
        "boundaries" : "_country_boundaries",
        "coastline" : "_country_coastline",
        "wikiDataQid" : "_country_wikiDataQid",
        "locationDesc" : "_country_locationDesc",
        "terrainDesc" : "_country_terrainDesc",
        "climateDesc" : "_country_climateDesc",
        "natResourcesDesc" : "_country_natResourcesDesc",
        "elevationMinPlace" : "_country_elevationMinPlace",
        "elevationMin" : "_country_elevationMin",
        "elevationMaxPlace" : "_country_elevationMaxPlace",
        "elevationMax" : "_country_elevationMax",
        "birthRate" : "_country_birthRate",
        "deathRate" : "_country_deathRate",
        "migrationRate" : "_country_migrationRate",
        "povertyRate" : "_country_povertyRate",
        "unemploymentRate" : "_country_unemploymentRate",
        "ageStructure" : "_country_ageStructure",
        "gdpByServices" : "_country_gdpByServices",
        "gdpByIndustry" : "_country_gdpByIndustry",
        "gdpByAgriculture" : "_country_gdpByAgriculture"
      }
    }
  } ],
  "isas" : [ {
    "var" : "country"
  } ],
  "isLambda" : false,
  "digest" : "jBNhfyovOx42HsFSLFRVnw=="
}