{
  "uri" : "local://Jj3W-SPLd-8THK3yDRimzD/",
  "name" : "Tunisia",
  "category" : "country",
  "parent" : "local://mm81nqJ9ApBu7qJNqC6UHB/",
  "pname" : "Country Profiles (Folder)",
  "flags" : "U",
  "lvars" : [ ],
  "vars" : [ {
    "name" : "_country_identifier",
    "expr" : {
      "str" : "ts",
      "strEditMode" : ""
    }
  }, {
    "name" : "_country_name",
    "expr" : {
      "str" : "Tunisia",
      "strEditMode" : ""
    }
  }, {
    "name" : "_country_longName",
    "expr" : {
      "str" : "Tunisian Republic",
      "strEditMode" : ""
    }
  }, {
    "name" : "_country_wpPageName",
    "expr" : {
      "str" : "Tunisia",
      "strEditMode" : ""
    }
  }, {
    "name" : "_country_population",
    "expr" : {
      "num" : 10835873
    }
  }, {
    "name" : "_country_gdpExchangeRate",
    "expr" : {
      "num" : 45610000000
    }
  }, {
    "name" : "_country_gdpPerCapitaPpp",
    "expr" : {
      "num" : 9900
    }
  }, {
    "name" : "_country_googlePlaceName",
    "expr" : {
      "str" : "",
      "strEditMode" : ""
    }
  }, {
    "name" : "_country_area",
    "expr" : {
      "num" : 163610
    }
  }, {
    "name" : "_country_boundaries",
    "expr" : {
      "num" : 1424
    }
  }, {
    "name" : "_country_coastline",
    "expr" : {
      "num" : 1148
    }
  }, {
    "name" : "_country_wikiDataQid",
    "expr" : {
      "str" : "Q948",
      "strEditMode" : ""
    }
  }, {
    "name" : "_country_locationDesc",
    "expr" : {
      "str" : "Northern Africa, bordering the Mediterranean Sea, between Algeria and Libya",
      "strEditMode" : ""
    }
  }, {
    "name" : "_country_terrainDesc",
    "expr" : {
      "str" : "mountains in north; hot, dry central plain; semiarid south merges into the Sahara",
      "strEditMode" : ""
    }
  }, {
    "name" : "_country_climateDesc",
    "expr" : {
      "str" : "temperate in north with mild, rainy winters and hot, dry summers; desert in south",
      "strEditMode" : ""
    }
  }, {
    "name" : "_country_natResourcesDesc",
    "expr" : {
      "str" : "petroleum, phosphates, iron ore, lead, zinc, salt",
      "strEditMode" : ""
    }
  }, {
    "name" : "_country_elevationMinPlace",
    "expr" : {
      "str" : "Shatt al Gharsah",
      "strEditMode" : ""
    }
  }, {
    "name" : "_country_elevationMin",
    "expr" : {
      "num" : -17
    }
  }, {
    "name" : "_country_elevationMaxPlace",
    "expr" : {
      "str" : "Jebel ech Chambi",
      "strEditMode" : ""
    }
  }, {
    "name" : "_country_elevationMax",
    "expr" : {
      "num" : 1544
    }
  }, {
    "name" : "_country_birthRate",
    "expr" : {
      "num" : 17
    }
  }, {
    "name" : "_country_deathRate",
    "expr" : {
      "num" : 6
    }
  }, {
    "name" : "_country_migrationRate",
    "expr" : {
      "num" : -2
    }
  }, {
    "name" : "_country_povertyRate",
    "expr" : {
      "num" : 3.8
    }
  }, {
    "name" : "_country_unemploymentRate",
    "expr" : {
      "num" : 17.4
    }
  }, {
    "name" : "_country_ageStructure",
    "expr" : {
      "json" : {
        "0-14" : 23,
        "15-24" : 16.5,
        "25-54" : 44.7,
        "55-64" : 8.1,
        "65-max" : 7.7
      }
    }
  }, {
    "name" : "_country_gdpByServices",
    "expr" : {
      "num" : 61.5
    }
  }, {
    "name" : "_country_gdpByIndustry",
    "expr" : {
      "num" : 29.6
    }
  }, {
    "name" : "_country_gdpByAgriculture",
    "expr" : {
      "num" : 8.9
    }
  }, {
    "name" : "country",
    "expr" : {
      "concept" : "local://RVV5lASBN39K6qUF_c6G2D/",
      "conceptName" : "Country",
      "bindings" : {
        "identifier" : "_country_identifier",
        "name" : "_country_name",
        "longName" : "_country_longName",
        "wpPageName" : "_country_wpPageName",
        "population" : "_country_population",
        "gdpExchangeRate" : "_country_gdpExchangeRate",
        "gdpPerCapitaPpp" : "_country_gdpPerCapitaPpp",
        "googlePlaceName" : "_country_googlePlaceName",
        "area" : "_country_area",
        "boundaries" : "_country_boundaries",
        "coastline" : "_country_coastline",
        "wikiDataQid" : "_country_wikiDataQid",
        "locationDesc" : "_country_locationDesc",
        "terrainDesc" : "_country_terrainDesc",
        "climateDesc" : "_country_climateDesc",
        "natResourcesDesc" : "_country_natResourcesDesc",
        "elevationMinPlace" : "_country_elevationMinPlace",
        "elevationMin" : "_country_elevationMin",
        "elevationMaxPlace" : "_country_elevationMaxPlace",
        "elevationMax" : "_country_elevationMax",
        "birthRate" : "_country_birthRate",
        "deathRate" : "_country_deathRate",
        "migrationRate" : "_country_migrationRate",
        "povertyRate" : "_country_povertyRate",
        "unemploymentRate" : "_country_unemploymentRate",
        "ageStructure" : "_country_ageStructure",
        "gdpByServices" : "_country_gdpByServices",
        "gdpByIndustry" : "_country_gdpByIndustry",
        "gdpByAgriculture" : "_country_gdpByAgriculture"
      }
    }
  } ],
  "isas" : [ {
    "var" : "country"
  } ],
  "isLambda" : false,
  "digest" : "TJ7ZT6Btuz6GpJHQxS0Qdw=="
}