{
  "uri" : "local://VYaEp6gy7R9tOKMpC0Tk9E/",
  "name" : "Luxembourg",
  "category" : "country",
  "parent" : "local://mm81nqJ9ApBu7qJNqC6UHB/",
  "pname" : "Country Profiles (Folder)",
  "flags" : "U",
  "lvars" : [ ],
  "vars" : [ {
    "name" : "_country_identifier",
    "expr" : {
      "str" : "lu",
      "strEditMode" : ""
    }
  }, {
    "name" : "_country_name",
    "expr" : {
      "str" : "Luxembourg",
      "strEditMode" : ""
    }
  }, {
    "name" : "_country_longName",
    "expr" : {
      "str" : "Grand Duchy of Luxembourg",
      "strEditMode" : ""
    }
  }, {
    "name" : "_country_wpPageName",
    "expr" : {
      "str" : "Luxembourg",
      "strEditMode" : ""
    }
  }, {
    "name" : "_country_population",
    "expr" : {
      "num" : 514862
    }
  }, {
    "name" : "_country_gdpExchangeRate",
    "expr" : {
      "num" : 56740000000
    }
  }, {
    "name" : "_country_gdpPerCapitaPpp",
    "expr" : {
      "num" : 81100
    }
  }, {
    "name" : "_country_googlePlaceName",
    "expr" : {
      "str" : "",
      "strEditMode" : ""
    }
  }, {
    "name" : "_country_area",
    "expr" : {
      "num" : 2586
    }
  }, {
    "name" : "_country_boundaries",
    "expr" : {
      "num" : 359
    }
  }, {
    "name" : "_country_coastline",
    "expr" : {
      "num" : 0
    }
  }, {
    "name" : "_country_wikiDataQid",
    "expr" : {
      "str" : "Q32",
      "strEditMode" : ""
    }
  }, {
    "name" : "_country_locationDesc",
    "expr" : {
      "str" : "Western Europe, between France and Germany",
      "strEditMode" : ""
    }
  }, {
    "name" : "_country_terrainDesc",
    "expr" : {
      "str" : "mostly gently rolling uplands with broad, shallow valleys; uplands to slightly mountainous in the north; steep slope down to Moselle flood plain in the southeast",
      "strEditMode" : ""
    }
  }, {
    "name" : "_country_climateDesc",
    "expr" : {
      "str" : "modified continental with mild winters, cool summers",
      "strEditMode" : ""
    }
  }, {
    "name" : "_country_natResourcesDesc",
    "expr" : {
      "str" : "iron ore (no longer exploited), arable land",
      "strEditMode" : ""
    }
  }, {
    "name" : "_country_elevationMinPlace",
    "expr" : {
      "str" : "Moselle River",
      "strEditMode" : ""
    }
  }, {
    "name" : "_country_elevationMin",
    "expr" : {
      "num" : 133
    }
  }, {
    "name" : "_country_elevationMaxPlace",
    "expr" : {
      "str" : "Buurgplaatz",
      "strEditMode" : ""
    }
  }, {
    "name" : "_country_elevationMax",
    "expr" : {
      "num" : 559
    }
  }, {
    "name" : "_country_birthRate",
    "expr" : {
      "num" : 12
    }
  }, {
    "name" : "_country_deathRate",
    "expr" : {
      "num" : 9
    }
  }, {
    "name" : "_country_migrationRate",
    "expr" : {
      "num" : 8
    }
  }, {
    "name" : "_country_povertyRate",
    "expr" : {
      "num" : 0
    }
  }, {
    "name" : "_country_unemploymentRate",
    "expr" : {
      "num" : 6
    }
  }, {
    "name" : "_country_ageStructure",
    "expr" : {
      "json" : {
        "0-14" : 18,
        "15-24" : 12.6,
        "25-54" : 42.3,
        "55-64" : 11.8,
        "65-max" : 15.2
      }
    }
  }, {
    "name" : "_country_gdpByServices",
    "expr" : {
      "num" : 86
    }
  }, {
    "name" : "_country_gdpByIndustry",
    "expr" : {
      "num" : 13.6
    }
  }, {
    "name" : "_country_gdpByAgriculture",
    "expr" : {
      "num" : 0.4
    }
  }, {
    "name" : "country",
    "expr" : {
      "concept" : "local://RVV5lASBN39K6qUF_c6G2D/",
      "conceptName" : "Country",
      "bindings" : {
        "identifier" : "_country_identifier",
        "name" : "_country_name",
        "longName" : "_country_longName",
        "wpPageName" : "_country_wpPageName",
        "population" : "_country_population",
        "gdpExchangeRate" : "_country_gdpExchangeRate",
        "gdpPerCapitaPpp" : "_country_gdpPerCapitaPpp",
        "googlePlaceName" : "_country_googlePlaceName",
        "area" : "_country_area",
        "boundaries" : "_country_boundaries",
        "coastline" : "_country_coastline",
        "wikiDataQid" : "_country_wikiDataQid",
        "locationDesc" : "_country_locationDesc",
        "terrainDesc" : "_country_terrainDesc",
        "climateDesc" : "_country_climateDesc",
        "natResourcesDesc" : "_country_natResourcesDesc",
        "elevationMinPlace" : "_country_elevationMinPlace",
        "elevationMin" : "_country_elevationMin",
        "elevationMaxPlace" : "_country_elevationMaxPlace",
        "elevationMax" : "_country_elevationMax",
        "birthRate" : "_country_birthRate",
        "deathRate" : "_country_deathRate",
        "migrationRate" : "_country_migrationRate",
        "povertyRate" : "_country_povertyRate",
        "unemploymentRate" : "_country_unemploymentRate",
        "ageStructure" : "_country_ageStructure",
        "gdpByServices" : "_country_gdpByServices",
        "gdpByIndustry" : "_country_gdpByIndustry",
        "gdpByAgriculture" : "_country_gdpByAgriculture"
      }
    }
  } ],
  "isas" : [ {
    "var" : "country"
  } ],
  "isLambda" : false,
  "digest" : "FhB9E1l702KctLSkg7ABzw=="
}