{
  "uri" : "local://be09VVBcyr8u9K8rX5XDEA/",
  "name" : "Commuter rails price is too high",
  "category" : ".issue",
  "parent" : "local://DZaELKgIJ8A-24Gmri6DPE/",
  "pname" : "Example Issue to Action",
  "flags" : "U",
  "lvars" : [ ],
  "vars" : [ {
    "name" : "issue",
    "expr" : {
      "str" : "Commuter rails price is too high"
    }
  }, {
    "name" : "audience",
    "expr" : {
      "str" : "students"
    }
  }, {
    "name" : "reason",
    "expr" : {
      "str" : "better discount"
    }
  }, {
    "name" : "createTime",
    "expr" : {
      "str" : "2014-12-02T15:51:31.154Z"
    }
  }, {
    "name" : "location",
    "expr" : {
      "json" : {
        "lat" : 42.484489499999995,
        "lon" : -71.2004989
      }
    }
  }, {
    "name" : "issueBind",
    "expr" : {
      "concept" : "local://a8nFL92qm5AL8awOWxStSD/",
      "conceptName" : "IssueLambda",
      "bindings" : {
        "issue" : "issue",
        "audience" : "audience",
        "reason" : "reason",
        "createTime" : "createTime",
        "location" : "location"
      }
    }
  } ],
  "isas" : [ {
    "var" : "issueBind"
  } ],
  "isLambda" : false,
  "digest" : "KN5/CbDVZ8ZCV5zS6S/qVQ=="
}